cicero/__init__.py
cicero/app.py
cicero/cli.py
cicero/git.py
cicero/images.py
cicero/main.py
cicero/preview.py
cicero/render.py
cicero/version.py
cicero/static/bootstrap/bootstrap-4.1.3.min.css
cicero/static/bootstrap/bootstrap-4.1.3.min.js
cicero/static/bootstrap/jquery-3.3.1.slim.min.js
cicero/static/bootstrap/popper-1.14.3.min.js
cicero/static/engines/remark-0.13.0/remark.css
cicero/static/engines/remark-0.13.0/remark.min.js
cicero/static/engines/remark-0.13.0/vendor.body.html
cicero/static/engines/remark-0.13.0/vendor.head.html
cicero/static/engines/remark-0.14.0/remark.css
cicero/static/engines/remark-0.14.0/remark.min.js
cicero/static/engines/remark-0.14.0/vendor.body.html
cicero/static/engines/remark-0.14.0/vendor.head.html
cicero/static/engines/remark-legacy/remark.css
cicero/static/engines/remark-legacy/remark.min.js
cicero/static/engines/remark-legacy/vendor.body.html
cicero/static/engines/remark-legacy/vendor.css
cicero/static/engines/remark-legacy/vendor.head.html
cicero/static/engines/reveal.js-3.7.0/vendor.body.html
cicero/static/engines/reveal.js-3.7.0/vendor.head.html
cicero/static/engines/reveal.js-3.7.0/css/reveal.css
cicero/static/engines/reveal.js-3.7.0/css/reveal.scss
cicero/static/engines/reveal.js-3.7.0/css/print/paper.css
cicero/static/engines/reveal.js-3.7.0/css/print/pdf.css
cicero/static/engines/reveal.js-3.7.0/css/theme/README.md
cicero/static/engines/reveal.js-3.7.0/css/theme/beige.css
cicero/static/engines/reveal.js-3.7.0/css/theme/black.css
cicero/static/engines/reveal.js-3.7.0/css/theme/blood.css
cicero/static/engines/reveal.js-3.7.0/css/theme/league.css
cicero/static/engines/reveal.js-3.7.0/css/theme/moon.css
cicero/static/engines/reveal.js-3.7.0/css/theme/night.css
cicero/static/engines/reveal.js-3.7.0/css/theme/serif.css
cicero/static/engines/reveal.js-3.7.0/css/theme/simple.css
cicero/static/engines/reveal.js-3.7.0/css/theme/sky.css
cicero/static/engines/reveal.js-3.7.0/css/theme/solarized.css
cicero-0.2.6.dist-info/entry_points.txt
cicero-0.2.6.dist-info/LICENSE
cicero-0.2.6.dist-info/WHEEL
cicero-0.2.6.dist-info/METADATA
cicero-0.2.6.dist-info/RECORD
