Metadata-Version: 2.1
Name: cicero
Version: 0.2.6
Summary: Cicero - Serving presentation slides written in Markdown.
Home-page: https://github.com/bast/cicero
Author: Radovan Bast
Author-email: radovan.bast@uit.no
Classifier: License :: OSI Approved :: GNU Affero General Public License v3
Requires-Dist: requests
Requires-Dist: flask < 3.0.0
Requires-Dist: black ; extra == "dev"
Requires-Dist: pytest ; extra == "test"
Provides-Extra: dev
Provides-Extra: test
